zenblog/__init__.py
zenblog/apps.py
zenblog/sitemaps.py
zenblog/urls.py
zenblog/views.py
zenblog/static/zenblog/css/main.css
zenblog/static/zenblog/css/variables.css
zenblog/static/zenblog/js/main.js
zenblog/static/zenblog/scss/_comments.scss
zenblog/static/zenblog/scss/_contact.scss
zenblog/static/zenblog/scss/_footer.scss
zenblog/static/zenblog/scss/_general.scss
zenblog/static/zenblog/scss/_header.scss
zenblog/static/zenblog/scss/_nav.scss
zenblog/static/zenblog/scss/_posts.scss
zenblog/static/zenblog/scss/main.scss
zenblog/static/zenblog/scss/variables.css
zenblog/static/zenblog/vendor/aos/aos.cjs.js
zenblog/static/zenblog/vendor/aos/aos.css
zenblog/static/zenblog/vendor/aos/aos.esm.js
zenblog/static/zenblog/vendor/aos/aos.js
zenblog/static/zenblog/vendor/aos/aos.js.map
zenblog/static/zenblog/vendor/bootstrap/css/bootstrap-grid.css
zenblog/static/zenblog/vendor/bootstrap/css/bootstrap-grid.css.map
zenblog/static/zenblog/vendor/bootstrap/css/bootstrap-grid.min.css
zenblog/static/zenblog/vendor/bootstrap/css/bootstrap-grid.min.css.map
zenblog/static/zenblog/vendor/bootstrap/css/bootstrap-grid.rtl.css
zenblog/static/zenblog/vendor/bootstrap/css/bootstrap-grid.rtl.css.map
zenblog/static/zenblog/vendor/bootstrap/css/bootstrap-grid.rtl.min.css
zenblog/static/zenblog/vendor/bootstrap/css/bootstrap-grid.rtl.min.css.map
zenblog/static/zenblog/vendor/bootstrap/css/bootstrap-reboot.css
zenblog/static/zenblog/vendor/bootstrap/css/bootstrap-reboot.css.map
zenblog/static/zenblog/vendor/bootstrap/css/bootstrap-reboot.min.css
zenblog/static/zenblog/vendor/bootstrap/css/bootstrap-reboot.min.css.map
zenblog/static/zenblog/vendor/bootstrap/css/bootstrap-reboot.rtl.css
zenblog/static/zenblog/vendor/bootstrap/css/bootstrap-reboot.rtl.css.map
zenblog/static/zenblog/vendor/bootstrap/css/bootstrap-reboot.rtl.min.css
zenblog/static/zenblog/vendor/bootstrap/css/bootstrap-reboot.rtl.min.css.map
zenblog/static/zenblog/vendor/bootstrap/css/bootstrap-utilities.css
django_zenblog_ds-5.0.5.dist-info/WHEEL
django_zenblog_ds-5.0.5.dist-info/METADATA
django_zenblog_ds-5.0.5.dist-info/RECORD
