Metadata-Version: 2.3
Name: django_zenblog_ds
Version: 5.0.5
Summary: Demiansoft template(zenblog)
Requires-Python: >=3.6
Requires-Dist: Django>=4.2.11
Requires-Dist: shared_lib_ds>=1.3.5
